{"_id":{"$oid":"615ffcbf0b36c16b76ab1e5d"},"description":"您的資產淨值約有多少比例可以用於投資？請注意，買賣投資產品可能帶來虧損。","answer1":"0%","answer2":"大過 0%至 50%","answer3":"大過 50%","answer_sum":"3","question_number":"1","final_question":"0","question_type":"Suitability_analysis","question_group":"Suitability_analysis"}
{"_id":{"$oid":"616d0f0a25fbfb36a968ee3c"},"description":"哪項描述最符合您為達到預期報酬而願意承受損失的程度？","answer1":"不能承受任何資本損失","answer2":"輕微的資本損失","answer3":"適度的資本損失","answer4":"較大的資本損失","answer_sum":"4","question_number":"2","final_question":"0","question_type":"Suitability_analysis","question_group":"Suitability_analysis"}
{"_id":{"$oid":"616d105125fbfb36a968ee3d"},"description":"哪一項最能描述您的投資目的？","answer1":"保障資本","answer2":"定期收入","answer3":"定期收入及資本成長","answer4":"長期資本成長","answer5":"大幅資本成長","answer_sum":"5","question_number":"3","final_question":"0","question_type":"Suitability_analysis","question_group":"Suitability_analysis"}
{"_id":{"$oid":"616d10fc25fbfb36a968ee3e"},"description":"選項顯示了 5 種不同投資組合在較短投資期間 (如 1 年) 內的潛在收益和損失，您認為哪一種投資組合最吸引您？ ","answer1":"投資組合 A － 接受 ±9% 的潛在收益和損失","answer2":"投資組合 B － 接受 ±16% 的潛在收益和損失","answer3":"投資組合 C － 接受 ±22% 的潛在收益和損失","answer4":"投資組合 D － 接受 ±28% 的潛在收益和損失","answer5":"投資組合 E － 接受 ±35% 的潛在收益和損失","answer_sum":"5","question_number":"4","final_question":"0","question_type":"Suitability_analysis","question_group":"Suitability_analysis"}
{"_id":{"$oid":"616d128325fbfb36a968ee3f"},"description":"倘若您的投資價格經過一段時間後由於市場波動而下跌，您會如何處置？","answer1":"即使跌幅輕微，也會立刻出售","answer2":"倘若下跌幅度較大，會將該投資全部出售","answer3":"倘若下跌幅度較大，會將該投資部分出售，保留其餘投資等待價格回升","answer4":"即使投資價格下跌，也不會出售，反而會願意等待其價值回升","answer5":"即使投資價格下跌，也不會出售，反而會考慮趁低進場","answer_sum":"5","question_number":"5","final_question":"0","question_type":"Suitability_analysis","question_group":"Suitability_analysis"}
{"_id":{"$oid":"616d12e425fbfb36a968ee40"},"description":"選項顯示 5 種不同投資組合在較長投資期間（如 10 年）的價格波動，您會選擇哪項投資？","answer1":"投資組合： 價格可能波動不大 (± 5% 波動)","answer2":"投資組合： 價格可能有微幅波動 (± 10% 波動)","answer3":"投資組合： 價格可能有適度波動 (± 15% 波動)","answer4":"投資組合： 價格可能有相當大幅波動 (± 20% 波動)","answer5":"投資組合： 價格可能大幅波動 (超過 ± 20% 波動)","answer_sum":"5","question_number":"6","final_question":"0","question_type":"Suitability_analysis","question_group":"Suitability_analysis"}
{"_id":{"$oid":"616d135c25fbfb36a968ee41"},"description":"您的年齡?","answer1":"70歲以上","answer2":"69-60歲","answer3":"59-45歲","answer4":"44-29歲","answer5":"28-20歲","answer_sum":"5","question_number":"7","final_question":"0","question_type":"Suitability_analysis","question_group":"Suitability_analysis"}
{"_id":{"$oid":"616d13c125fbfb36a968ee43"},"description":"您有以下何種學歷來幫助您理解投資和保險產品?","answer1":"博士碩士","answer2":"大學","answer3":"專科","answer4":"高中高職","answer5":"以上皆非","answer_sum":"5","question_number":"8","final_question":"0","question_type":"Suitability_analysis","question_group":"Suitability_analysis"}
{"_id":{"$oid":"616d148225fbfb36a968ee44"},"description":"請選擇 (可複選) 以下您曾經 (含目前) 持有和具備相關知識的投資商品。","answer1":"無任何投資經驗 (僅持有非投資型保單)","answer2":"投資型保單商品","answer3":"大宗商品、認股權證、選擇權、期貨等衍生性金融商品或結構型產品","answer4":"基金或 ETF","answer5":"股票、債券或外匯","answer_sum":"5","question_number":"9","final_question":"0","question_type":"Suitability_analysis_multiple","question_group":"Suitability_analysis"}
{"_id":{"$oid":"616d15f125fbfb36a968ee45"},"description":"您的實務經驗 (如在過去 10 年內有 3 年以上工作經驗) 是否可協助理解投資和保險產品?","answer1":"是","answer2":"否","answer_sum":"2","question_number":"10","final_question":"0","question_type":"Suitability_analysis","question_group":"Suitability_analysis"}
{"_id":{"$oid":"616d167b25fbfb36a968ee46"},"description":"下列何種投資經驗的敘述最能描述您在投資方面的情況(包含投資時間和投資產品)?","answer1":"無任何投資經驗","answer2":"有限 (幾乎沒有任何投資經驗)，但欲學習更多投資相關的內容","answer3":"一般 (擁有一些投資經驗)，但沒有興趣再學習任何投資相關的內容","answer4":"一般 (擁有一些投資經驗)，且同時對投資領域有興趣","answer5":"廣泛 (擁有相當的投資經驗)，且對投資決定感到有信心","answer_sum":"5","question_number":"11","final_question":"0","question_type":"Suitability_analysis","question_group":"Suitability_analysis"}
{"_id":{"$oid":"616d16e825fbfb36a968ee47"},"description":"為達成您的投資目標，請問您願意持有的投資年限最長為?","answer1":"少於 3 年","answer2":"介於 3 年至 5 年 (含)","answer3":"介於 5 年至 10 年 (含)","answer4":"10 年以上","answer_sum":"4","question_number":"12","final_question":"1","question_type":"Suitability_analysis","question_group":"Suitability_analysis"}
{"_id":{"$oid":"616fbb4616991cb97043a145"},"description":"您的年齡","answerA":"57歲以上","answerB":"57-46歲","answerC":"45-34歲","answerD":"33-22歲","answerE":"22歲以下","answer_sum":"5","question_number":"1","final_question":"0","question_group":"Car_insurance_planning"}
{"_id":{"$oid":"616fbd8416991cb97043a146"},"description":"您的性別","answerA":"男","answerB":"女","answer_sum":"2","question_number":"2","final_question":"0","question_group":"Car_insurance_planning"}
{"_id":{"$oid":"616fbdbd16991cb97043a147"},"description":"過去五年的肇事紀錄","answerA":"無","answerB":"過去僅一次肇事","answerC":"過去二次肇事","answerD":"過去三次肇事","answerE":"每年有一次以上肇事","answer_sum":"5","question_number":"3","final_question":"0","question_group":"Car_insurance_planning"}
{"_id":{"$oid":"616fbe3b16991cb97043a148"},"description":"過去五年有幾年沒有任何賠款","answerA":"五年沒有任何賠款","answerB":"四年沒有任何賠款","answerC":"三年沒有任何賠款","answerD":"二年沒有任何賠款","answerE":"五年均有賠款","answer_sum":"5","question_number":"4","final_question":"0","question_group":"Car_insurance_planning"}
{"_id":{"$oid":"616fbe8816991cb97043a149"},"description":"取得駕照有幾年時間","answerA":"新手","answerB":"五年內","answerC":"6至10年","answerD":"10年以上","answer_sum":"4","question_number":"5","final_question":"0","question_group":"Car_insurance_planning"}
{"_id":{"$oid":"616fc7f1e43741350c7f08f3"},"description":"家中是否有車庫","answerA":"無","answerB":"有","answer_sum":"2","final_question":"0","question_group":"Car_insurance_planning","question_number":"6"}
{"_id":{"$oid":"616fc7f1e43741350c7f08fe"},"description":"汽車種類","answerA":"國產車二年內新車","answerB":"進口汽車三年內","answerC":"國產車二年以上-八年","answerD":"進口汽車三年以上至十年","answerE":"以上皆非","answer_sum":"5","final_question":"0","question_group":"Car_insurance_planning","question_number":"7"}
{"_id":{"$oid":"616fc7f1e43741350c7f0909"},"description":"職業類別","answerA":"內勤人員不需外出","answerB":"外勤人士每天外出","answerC":"內勤人員每周一次外出洽公或外勤人士並非每天外出","answer_sum":"3","final_question":"0","question_group":"Car_insurance_planning","question_number":"8"}
{"_id":{"$oid":"616fc7f1e43741350c7f091d"},"description":"對於汽車被撞凹、刮花   您的重視程度(一分_為不在意 至十分_極為在意)","answerA":"一分","answerB":"二分","answerC":"三至五分","answerD":"六至九分","answerE":"十分","answer_sum":"5","final_question":"0","question_group":"Car_insurance_planning","question_number":"9"}
{"_id":{"$oid":"616fc7f1e43741350c7f0927"},"description":"對於汽車失竊   產生代步 生活不便利性程度(一分_為不在意 至十分_極為在意)","answerA":"一分","answerB":"二分","answerC":"三至五分","answerD":"六至九分","answerE":"十分","answer_sum":"5","final_question":"0","question_group":"Car_insurance_planning","question_number":"10"}
{"_id":{"$oid":"616fc7f1e43741350c7f0931"},"description":"假設與他車發生車禍   產生焦慮訴訟重視程度(一分_為不在意 至十分_極為在意)","answerA":"一分","answerB":"二分","answerC":"三至五分","answerD":"六至九分","answerE":"十分","answer_sum":"5","final_question":"1","question_group":"Car_insurance_planning","question_number":"11"}


{"_id":{"$oid":"619c84f874f9b53cb390f5fa"},"description":"年齡(實歲)","answer1":"0-3","answer1_count":"","answer2":"4-18","answer2_count":"","answer3":"19-27","answer3_count":"","answer4":"28-34","answer4_count":"","answer5":"35-45","answer5_count":"","answer6":"46-65","answer6_count":"","answer_sum":"6","question_number":"1","final_question":"0","question_type":"Life_stage1","question_group":"Life_stage1"}
{"_id":{"$oid":"619c850f74f9b53cb390f5fb"},"description":"性別","answer1":"男","answer1_count":"","answer2":"女","answer2_count":"","answer_sum":"2","question_number":"2","final_question":"0","question_type":"Life_stage1","question_group":"Life_stage1"}
{"_id":{"$oid":"619c850f74f9b53cb390f5fc"},"description":"您目前的職業?","answer1":"軍公教","answer1_count":"","answer2":"服務業","answer2_count":"","answer3":"製造業","answer3_count":"","answer_sum":"3","question_number":"3","final_question":"0","question_type":"Life_stage1","question_group":"Life_stage1"}
{"_id":{"$oid":"619c850f74f9b53cb390f5fd"},"description":"個人是否為家庭的主要經濟來源","answer1":"是","answer1_count":"","answer2":"否","answer2_count":"","answer_sum":"2","question_number":"4","final_question":"0","question_type":"Life_stage1","question_group":"Life_stage1"}
{"_id":{"$oid":"619c850f74f9b53cb390f5fe"},"description":"婚姻狀況","answer1":"已婚","answer1_count":"","answer2":"未婚","answer2_count":"","answer_sum":"2","question_number":"5","final_question":"0","question_type":"Life_stage1","question_group":"Life_stage1"}
{"_id":{"$oid":"619c850f74f9b53cb390f5ff"},"description":"家庭成員(子女人數) ","answer1":"0","answer1_count":"","answer2":"1","answer2_count":"","answer3":"2","answer3_count":"","answer4":"3","answer4_count":"","answer5":">3","answer5_count":"","answer_sum":"5","question_number":"6","final_question":"0","question_type":"Life_stage1","question_group":"Life_stage1"}
{"_id":{"$oid":"619c854e74f9b53cb390f601"},"description":"最高學歷","answer1":"博士、碩士","answer1_count":"","answer2":"大學、專科","answer2_count":"","answer3":"高中、職","answer3_count":"","answer4":"國中","answer4_count":"","answer_sum":"4","question_number":"7","final_question":"0","question_type":"Life_stage1","question_group":"Life_stage1"}
{"_id":{"$oid":"619c8d2274f9b53cb390f609"},"description":"平均工作時間 小時/週","answer1":"0小時","answer1_count":"","answer2":"40小時","answer2_count":"","answer3":"48小時","answer3_count":"","answer4":"60小時","answer4_count":"","answer5":"其他","answer5_count":"","answer_sum":"5","question_number":"8","final_question":"0","question_type":"Life_stage1","question_group":"Life_stage1"}
{"_id":{"$oid":"619c854e74f9b53cb390f602"},"description":"家庭月所得狀況","answer1":"5萬元以下","answer1_count":"","answer2":"5萬以上~10萬","answer2_count":"","answer3":"10萬以上~15萬","answer3_count":"","answer4":"其他","answer4_count":"","answer_sum":"4","question_number":"9","final_question":"0","question_type":"Life_stage1","question_group":"Life_stage1"}
{"_id":{"$oid":"619c854e74f9b53cb390f603"},"description":"負債多少？房貸.車貸.信貸.學貸等","answer1":"無","answer1_count":"","answer2":"五十萬以下","answer2_count":"","answer3":"50-100","answer3_count":"","answer4":"100-500","answer4_count":"","answer5":"500-1000","answer5_count":"","answer6":"超過一千萬","answer6_count":"","answer_sum":"6","question_number":"10","final_question":"0","question_type":"Life_stage1","question_group":"Life_stage1"}
{"_id":{"$oid":"619c854e74f9b53cb390f604"},"description":"您目前現有理財規劃有(可複選)","answer1":"活儲、定存等利息收入","answer1_count":"","answer2":"不動產(房租收入)","answer2_count":"","answer3":"銀行外幣存款、基金或股票","answer3_count":"","answer4":"投資型保單儲蓄險","answer4_count":"","answer5":"其他","answer5_count":"","answer_sum":"5","question_number":"11","final_question":"0","question_type":"Life_stage1","question_group":"Life_stage1"}
{"_id":{"$oid":"619c854e74f9b53cb390f605"},"description":"您目前擁有哪些保險？ (可複選)","answer1":"勞健保","answer1_count":"","answer2":"國民年金保險","answer2_count":"","answer3":"公保或軍保","answer3_count":"","answer4":"公司團保","answer4_count":"","answer5":"農保","answer5_count":"","answer_sum":"5","question_number":"12","final_question":"0","question_type":"Life_stage1","question_group":"Life_stage1"}
{"_id":{"$oid":"619c854e74f9b53cb390f606"},"description":"您認為目前多少保險額度才足夠呢?","answer1":"100萬~300萬","answer1_count":"","answer2":"300萬~500萬","answer2_count":"","answer3":"500萬~1000萬","answer3_count":"","answer4":"其他","answer4_count":"","answer_sum":"4","question_number":"13","final_question":"0","question_type":"Life_stage1","question_group":"Life_stage1"}
{"_id":{"$oid":"619c854e74f9b53cb390f607"},"description":"除了家庭支出外,您可接受保費預算如何?(每個月)","answer1":"1000元-5000元內","answer1_count":"","answer2":"5000元~1萬元內","answer2_count":"","answer3":"1萬元~3萬元內","answer3_count":"","answer4":"3萬元~5萬元內","answer4_count":"","answer5":"其他","answer5_count":"","answer_sum":"5","question_number":"14","final_question":"0","question_type":"Life_stage1","question_group":"Life_stage1"}
{"_id":{"$oid":"619c854e74f9b53cb390f608"},"description":"過去五年內是否曾因受傷或生病住院治療七日以上？誠實告知將可免去未來不必要的理賠爭議。","answer1":"是","answer1_count":"","answer2":"否","answer2_count":"","answer_sum":"2","question_number":"15","final_question":"1","question_type":"Life_stage1","question_group":"Life_stage1"}


{"_id":{"$oid":"619a60f1b3ec6cd2149cb198"},"description":"商4-第一題","answer1":"A","answer2":"B","answer3":"C","answer4":"D","answer5":"E","answer_sum":"5","question_number":"1","final_question":"0","question_type":"Life_stage","question_group":"Life_stage"}
{"_id":{"$oid":"619a6110b3ec6cd2149cb199"},"description":"商4-第二題","answer1":"A","answer2":"B","answer3":"C","answer4":"D","answer5":"E","answer_sum":"5","question_number":"2","final_question":"0","question_type":"Life_stage","question_group":"Life_stage"}
{"_id":{"$oid":"619a6110b3ec6cd2149cb200"},"description":"商4-第三題","answer1":"A","answer2":"B","answer3":"C","answer4":"D","answer5":"E","answer_sum":"5","question_number":"3","final_question":"0","question_type":"Life_stage","question_group":"Life_stage"}
{"_id":{"$oid":"619a6110b3ec6cd2149cb201"},"description":"商4-第四題","answer1":"A","answer2":"B","answer3":"C","answer4":"D","answer5":"E","answer_sum":"5","question_number":"4","final_question":"0","question_type":"Life_stage","question_group":"Life_stage"}
{"_id":{"$oid":"619a6110b3ec6cd2149cb202"},"description":"商4-第五題","answer1":"A","answer2":"B","answer3":"C","answer4":"D","answer5":"E","answer_sum":"5","question_number":"5","final_question":"1","question_type":"Life_stage","question_group":"Life_stage"}


{"_id":{"$oid": "619a42c9757d0185e37a583a"},"description":"請問你結婚了嗎？","answer1": "未婚","answer2": "已婚","answer_sum": "2","question_number": "1","final_question": "0","can_skip": true,"skip_answer": "1","skip_to_question": "3","skip_answer_value": "2:0","question_type": "guarantee_gap_analysis","question_group": "guarantee_gap_analysis"}
{"_id":{"$oid": "619a42f1757d0185e37a583b"},"description":"你的配偶每年的收入大約是多少？","answer1": "無","answer2": "40萬以下","answer3": "41 - 60萬","answer4": "61 - 80萬","answer5": "81 - 100萬","answer6": "101 - 150萬","answer7": "151 - 200萬","answer8": "201萬以上","answer1_value": "0","answer2_value": "20","answer3_value": "50","answer4_value": "70","answer5_value": "90","answer6_value": "125","answer7_value": "175","answer8_value": "225","answer_sum": "8","question_number": "2","final_question": "0","can_skip": false,"question_type": "guarantee_gap_analysis_answer","question_group": "guarantee_gap_analysis"}
{"_id":{"$oid": "619a4334757d0185e37a583c"},"description":"請問你有幾位小孩？","answer1": "無","answer2": "1位","answer3": "2位","answer4": "3位","answer5": "4位（含）以上","answer1_value": "0","answer2_value": "1","answer3_value": "2","answer4_value": "3","answer5_value": "4","answer_sum": "5","question_number": "3","final_question": "0","can_skip": true,"skip_answer": "1","skip_to_question": "6","skip_answer_value": "4:0-5:0","question_type": "guarantee_gap_analysis_answer","question_group": "guarantee_gap_analysis"}
{"_id":{"$oid": "619a438c757d0185e37a583d"},"description":"你打算培養小孩到何種教育程度？","answer1": "高中（職）","answer2": "大學","answer3": "碩士","answer4": "博士","answer_sum": "4","question_number": "4","final_question": "0","can_skip": false,"question_type": "guarantee_gap_analysis","question_group": "guarantee_gap_analysis"}
{"_id":{"$oid": "619a43ac757d0185e37a583e"},"description":"你預估培育一位小孩到上述的教育程度約需多少花費（含才藝班、安親班等）？（提示：公立小學至大學約200萬，國外研究所另外加約300萬元）","answer1": "150萬以下","answer2": "151 - 250萬","answer3": "251 - 300萬","answer4": "301 - 350萬","answer5": "351 - 400萬","answer6": "401 - 450萬","answer7": "451 - 500萬","answer8": "501萬以上","answer1_value": "125","answer2_value": "200","answer3_value": "275","answer4_value": "325","answer5_value": "375","answer6_value": "425","answer7_value": "475","answer8_value": "525","answer_sum": "8","question_number": "5","final_question": "0","can_skip": false,"question_type": "guarantee_gap_analysis_answer","question_group": "guarantee_gap_analysis"}
{"_id":{"$oid": "619a43c0757d0185e37a583f"},"description":"請問你是否有房屋貸款？總額多少？","answer1": "無貸款","answer2": "100萬以下","answer3": "101 - 200萬","answer4": "201 - 300萬","answer5": "301 - 400萬","answer6": "401 - 500萬","answer7": "501 - 600萬","answer8": "601 - 700萬","answer9": "701 - 800萬","answer10": "801 - 900萬","answer11": "901 - 1000萬","answer12": "1001萬以上","answer1_value": "0","answer2_value": "50","answer3_value": "150","answer4_value": "250","answer5_value": "350","answer6_value": "450","answer7_value": "550","answer8_value": "650","answer9_value": "750","answer10_value": "850","answer11_value": "950","answer12_value": "1050","answer_sum": "12","question_number": "6","final_question": "0","can_skip": false,"question_type": "guarantee_gap_analysis_answer","question_group": "guarantee_gap_analysis"}
{"_id":{"$oid": "619a43d6757d0185e37a5840"},"description":"請問你是否有租賃房屋？每個月的房租是多少？","answer1": "無租屋","answer2": "1萬元以下","answer3": "1.1 - 2萬","answer4": "2.1 - 3萬","answer5": "3.1 - 4萬","answer6": "4.1 - 5萬","answer7": "5.1 - 6萬","answer8": "6.1萬以上","answer1_value": "0","answer2_value": "6","answer3_value": "18","answer4_value": "30","answer5_value": "43","answer6_value": "54","answer7_value": "66","answer8_value": "78","answer_sum": "8","question_number": "7","final_question": "0","can_skip": true,"skip_answer": "1","skip_to_question": "9","skip_answer_value": "8:0","question_type": "guarantee_gap_analysis_answer","question_group": "guarantee_gap_analysis"}
{"_id":{"$oid": "619a43ea757d0185e37a5841"},"description":"你預計還會續租多久？","answer1": "1年以下","answer2": "2年","answer3": "3年","answer4": "4年","answer5": "5年","answer6": "6年以上","answer1_value": "1","answer2_value": "2","answer3_value": "3","answer4_value": "4","answer5_value": "5","answer6_value": "6","answer_sum": "6","question_number": "8","final_question": "0","can_skip": false,"question_type": "guarantee_gap_analysis_answer","question_group": "guarantee_gap_analysis"}
{"_id":{"$oid": "619a43fa757d0185e37a5842"},"description":"請問你希望為自己準備多少喪葬費用？","answer1": "40萬以下","answer2": "41 - 50萬","answer3": "51 - 60萬","answer4": "61 - 70萬","answer5": "71 - 80萬","answer6": "81萬以上","answer1_value": "35","answer2_value": "45","answer3_value": "55","answer4_value": "65","answer5_value": "75","answer6_value": "85","answer_sum": "6","question_number": "9","final_question": "0","can_skip": false,"question_type": "guarantee_gap_analysis_answer","question_group": "guarantee_gap_analysis"}
{"_id":{"$oid": "619a440f757d0185e37a5843"},"description":"你有多少其他尚未清償的借款？（如：會錢、信用卡、汽車貸款等）","answer1": "無","answer2": "50萬以下","answer3": "51 - 100萬","answer4": "101 - 150萬","answer5": "151 - 200萬","answer6": "200萬以上","answer1_value": "0","answer2_value": "25","answer3_value": "75","answer4_value": "125","answer5_value": "175","answer6_value": "225","answer_sum": "6","question_number": "10","final_question": "0","can_skip": false,"question_type": "guarantee_gap_analysis_answer","question_group": "guarantee_gap_analysis"}
{"_id":{"$oid": "619a4421757d0185e37a5844"},"description":"你希望為家庭準備多少應急費用？（如：家人傷病費、汽修費、房屋修繕等）","answer1": "無","answer2": "20萬以下","answer3": "21 - 100萬","answer4": "101 - 150萬","answer5": "151 - 300萬","answer6": "301 - 400萬","answer7": "401 - 500萬","answer8": "501萬以上","answer1_value": "0","answer2_value": "15","answer3_value": "50","answer4_value": "125","answer5_value": "200","answer6_value": "350","answer7_value": "450","answer8_value": "550","answer_sum": "8","question_number": "11","final_question": "0","can_skip": false,"question_type": "guarantee_gap_analysis_answer","question_group": "guarantee_gap_analysis"}
{"_id":{"$oid": "619a4432757d0185e37a5845"},"description":"你每個月家庭的開銷（如：食、衣、住、行、稅、交際、父母孝養費、有小孩加褓母費等）","answer1": "1萬以下","answer2": "1.1 - 3萬","answer3": "3.1 - 4萬","answer4": "4.1 - 5萬","answer5": "5.1 - 7萬","answer6": "7.1 - 8萬","answer7": "8.1 - 10萬","answer8": "10萬以上","answer1_value": "6","answer2_value": "24","answer3_value": "42","answer4_value": "54","answer5_value": "72","answer6_value": "90","answer7_value": "108","answer8_value": "126","answer_sum": "8","question_number": "12","final_question": "0","can_skip": false,"question_type": "guarantee_gap_analysis_answer","question_group": "guarantee_gap_analysis"}
{"_id":{"$oid": "619a4442757d0185e37a5846"},"description":"你希望身後為家人留多少年的生活費？","answer1": "5年以下","answer2": "6 - 10年","answer3": "11 - 15年","answer4": "16 - 20年","answer5": "21 - 25年","answer6": "26年以上","answer1_value": "3","answer2_value": "8","answer3_value": "13","answer4_value": "18","answer5_value": "23","answer6_value": "28","answer_sum": "6","question_number": "13","final_question": "0","can_skip": false,"question_type": "guarantee_gap_analysis_answer","question_group": "guarantee_gap_analysis"}
{"_id":{"$oid": "619a4456757d0185e37a5847"},"description":"請問除了工作收入外，你是否還有其他年收入（如：利息、租金、稿費、合夥生意等）？","answer1": "無","answer2": "20萬以下","answer3": "21 - 30萬","answer4": "31 - 40萬","answer5": "41 - 50萬","answer6": "51萬以上","answer1_value": "0","answer2_value": "15","answer3_value": "25","answer4_value": "35","answer5_value": "45","answer6_value": "55","answer_sum": "6","question_number": "14","final_question": "0","can_skip": false,"question_type": "guarantee_gap_analysis_answer","question_group": "guarantee_gap_analysis"}
{"_id":{"$oid": "619a4468757d0185e37a5848"},"description":"你目前擁有多少一般身故的保障？","answer1": "無","answer2": "100萬以下","answer3": "101 - 200萬","answer4": "201 - 300萬","answer5": "301 - 400萬","answer6": "401 - 500萬","answer7": "501 - 600萬","answer8": "601 - 700萬","answer9": "701 - 800萬","answer10": "801 - 900萬","answer11": "901 - 1000萬","answer12": "1001萬以上","answer1_value": "0","answer2_value": "50","answer3_value": "150","answer4_value": "250","answer5_value": "350","answer6_value": "450","answer7_value": "550","answer8_value": "650","answer9_value": "750","answer10_value": "850","answer11_value": "950","answer12_value": "1050","answer_sum": "12","question_number": "15","final_question": "0","can_skip": false,"question_type": "guarantee_gap_analysis_answer","question_group": "guarantee_gap_analysis"}
{"_id":{"$oid": "619a4479757d0185e37a5849"},"description":"你目前約有多少銀行存款？","answer1": "無","answer2": "30萬以下","answer3": "31 - 50萬","answer4": "51 - 100萬","answer5": "101 - 150萬","answer6": "151 - 200萬","answer7": "201 - 300萬","answer8": "301 - 400萬","answer9": "401 - 500萬","answer10": "501萬以上","answer1_value": "0","answer2_value": "15","answer3_value": "40","answer4_value": "75","answer5_value": "125","answer6_value": "175","answer7_value": "250","answer8_value": "350","answer9_value": "450","answer10_value": "550","answer_sum": "10","question_number": "16","final_question": "0","can_skip": false,"question_type": "guarantee_gap_analysis_answer","question_group": "guarantee_gap_analysis"}
{"_id":{"$oid": "619a4489757d0185e37a584a"},"description":"你目前從事投資的金額約為多少？（如：股票、基金、債券等）","answer1": "無","answer2": "30萬以下","answer3": "31 - 50萬","answer4": "51 - 100萬","answer5": "101 - 150萬","answer6": "151 - 200萬","answer7": "201 - 300萬","answer8": "301 - 400萬","answer9": "401 - 500萬","answer10": "501萬以上","answer1_value": "0","answer2_value": "15","answer3_value": "40","answer4_value": "75","answer5_value": "125","answer6_value": "175","answer7_value": "250","answer8_value": "350","answer9_value": "450","answer10_value": "550","answer_sum": "10","question_number": "17","final_question": "0","can_skip": false,"question_type": "guarantee_gap_analysis_answer","question_group": "guarantee_gap_analysis"}
{"_id":{"$oid": "619a4489757d0185e37a584b"},"description":"你的年齡？","answer1": "0 ~ 18","answer2": "19 ~ 30","answer3": "31 ~ 50","answer4": "50以上","answer1_value": "10","answer2_value": "29","answer3_value": "33","answer4_value": "65","answer_sum": "4","question_number": "18","final_question": "1","can_skip": false,"question_type": "guarantee_gap_analysis_answer","question_group": "guarantee_gap_analysis"}


{"_id": {"$oid": "61cd62932d7995d4bcadde3d"}, "description": "請問您的 年齡 為何？", "field_name": "age", "question_number": "1", "final_question": "0", "question_type": "joint_financial_planning", "question_group": "joint_financial_planning"}
{"_id": {"$oid": "61cd62942d7995d4bcadde3e"}, "description": "請問您的 性別 為何？", "field_name": "gender", "question_number": "2", "final_question": "0", "question_type": "joint_financial_planning", "question_group": "joint_financial_planning"}
{"_id": {"$oid": "61cd62942d7995d4bcadde3f"}, "description": "請問您的 兒女數量 為何？", "field_name": "kid", "question_number": "3", "final_question": "0", "question_type": "joint_financial_planning", "question_group": "joint_financial_planning"}
{"_id": {"$oid": "61cd62942d7995d4bcadde40"}, "description": "請問您的 投資報酬率 為何？(單位 %)", "field_name": "ROI", "question_number": "4", "final_question": "0", "question_type": "joint_financial_planning", "question_group": "joint_financial_planning"}
{"_id": {"$oid": "61cd62942d7995d4bcadde41"}, "description": "請問 通貨膨脹率 為何？(單位 %)", "field_name": "CPI", "question_number": "5", "final_question": "0", "question_type": "joint_financial_planning", "question_group": "joint_financial_planning"}
{"_id": {"$oid": "61cd62942d7995d4bcadde42"}, "description": "請問您 目前可投資金額 為何？(單位 萬)", "field_name": "investable_amount", "question_number": "6", "final_question": "0", "question_type": "joint_financial_planning", "question_group": "joint_financial_planning"}
{"_id": {"$oid": "61cd62942d7995d4bcadde43"}, "description": "請問您的 薪資年收入 為何？(單位 萬)", "field_name": "salary", "question_number": "7", "final_question": "0", "question_type": "joint_financial_planning", "question_group": "joint_financial_planning"}
{"_id": {"$oid": "61cd62942d7995d4bcadde44"}, "description": "請問您的 其他年收入 為何？(單位 萬)", "field_name": "income", "question_number": "8", "final_question": "0", "question_type": "joint_financial_planning", "question_group": "joint_financial_planning"}
{"_id": {"$oid": "61cd62942d7995d4bcadde45"}, "description": "請問您的 一般家用年支出 為何？(單位 萬)", "field_name": "cost", "question_number": "9", "final_question": "0", "question_type": "joint_financial_planning", "question_group": "joint_financial_planning"}
{"_id": {"$oid": "61cd62942d7995d4bcadde46"}, "description": "請問您的 貸款年支出 為何？(單位 萬)", "field_name": "loan", "question_number": "10", "final_question": "0", "question_type": "joint_financial_planning", "question_group": "joint_financial_planning"}
{"_id": {"$oid": "61cd62942d7995d4bcadde47"}, "description": "請問您的 其他年費用 為何？(單位 萬)", "field_name": "expenditure", "question_number": "11", "final_question": "0", "question_type": "joint_financial_planning", "question_group": "joint_financial_planning"}
{"_id": {"$oid": "61cd62942d7995d4bcadde48"}, "description": "請問您的 電子郵件地址 為何？", "field_name": "email", "question_number": "12", "final_question": "1", "question_type": "joint_financial_planning", "question_group": "joint_financial_planning"}